[
{"title": "Fireball Pumpkin Pie"},
{"title": "Peanut Butter Whipped Cream Frosting"},
{"title": "Tiramisu Cookies"},
{"title": "French Butter Cookies"},
{"title": "Peanut Butter Coconut Cookies"},
{"title": "Peanut Butter and Jelly Overnight Oats"},
{"title": "Game-Day Thai Chicken Meatballs"},
{"title": "Apple Cake for Passover"},
{"title": "No-Bake Peanut Butter Oatmeal Bars"},
{"title": "Chocolate Peanut Butter Dream Bars"},
{"title": "Air Fryer Roasted Green Beans"},
{"title": "Easy Cast-Iron Peach Biscuit Rolls"},
{"title": "Chocolate Peanut Butter Overnight Oats"},
{"title": "Peanut Butter Chocolate Chip Brownies"},
{"title": "Bee Sting Cake"},
{"title": "Crudite Dip"},
{"title": "Rhubarb and Honey Chicken"},
{"title": "Instant Pot Corn Chowder"},
{"title": "Air Fryer Potato Chips"},
{"title": "Instant Pot Clam Chowder"}
]